sofia_agent/__init__.py
sofia_agent/cli.py
sofia_agent/config.py
sofia_agent/constants.py
sofia_agent/core.py
sofia_agent/llms/__init__.py
sofia_agent/llms/base.py
sofia_agent/llms/google.py
sofia_agent/llms/mistral.py
sofia_agent/llms/openai.py
sofia_agent/models/__init__.py
sofia_agent/models/flow.py
sofia_agent/models/tool.py
sofia_agent/types.py
sofia_agent/utils/__init__.py
sofia_agent/utils/logging.py
sofia_agent/utils/tracing.py
sofia_agent/utils/utils.py
sofia_agent-0.1.12.dist-info/LICENSE
sofia_agent-0.1.12.dist-info/METADATA
sofia_agent-0.1.12.dist-info/WHEEL
sofia_agent-0.1.12.dist-info/entry_points.txt
sofia_agent-0.1.12.dist-info/RECORD
