Metadata-Version: 2.3
Name: sofia-agent
Version: 0.1.12
Summary: SOFIA: Simple Orchestrated Flow Intelligence Agent
License: MIT
Author: chandralegend
Author-email: irugalbandarachandra@gmail.com
Requires-Python: >=3.12,<4.0
Classifier: License :: OSI Approved :: MIT License
Classifier: Programming Language :: Python :: 3
Classifier: Programming Language :: Python :: 3.12
Classifier: Programming Language :: Python :: 3.13
Provides-Extra: cli
Provides-Extra: gemini
Provides-Extra: mistralai
Provides-Extra: openai
Provides-Extra: traces
Requires-Dist: docstring-parser (>=0.16,<0.17)
Requires-Dist: google-genai (>=1.12.1,<2.0.0) ; extra == "gemini"
Requires-Dist: loguru (>=0.7.3,<0.8.0)
Requires-Dist: mistralai (>=1.7.0,<2.0.0) ; extra == "mistralai"
Requires-Dist: openai (>=1.76.0,<2.0.0) ; extra == "openai"
Requires-Dist: opentelemetry-api (>=1.33.0,<2.0.0) ; extra == "traces"
Requires-Dist: opentelemetry-exporter-otlp (>=1.33.0,<2.0.0) ; extra == "traces"
Requires-Dist: opentelemetry-instrumentation (>=0.54b0,<0.55) ; extra == "traces"
Requires-Dist: opentelemetry-sdk (>=1.33.0,<2.0.0) ; extra == "traces"
Requires-Dist: pydantic (>=2.11.3,<3.0.0)
Requires-Dist: pydantic-settings (>=2.9.1,<3.0.0)
Requires-Dist: pyyaml (>=6.0.2,<7.0.0)
Requires-Dist: questionary (>=2.1.0,<3.0.0) ; extra == "cli"
